{
  "type": "FeatureCollection",
  "features": [

    {
      "type": "Feature",
      "geometry": {
        "type": "Point",
        "coordinates": [7.63955,50.77113]
      },
      "properties": {
        "name": "Geilhausen",
        "category": "Germany",
        "visible": true
      }
    },

    {
      "type": "Feature",
      "geometry": {
        "type": "Point",
        "coordinates": [8.2007087,60.5326162]
      },
      "properties": {
        "name": "Geilo",
        "category": "Norway",
        "visible": true
      }
    }

  ]
}
